LICENSE
README.md
setup.py
macos_virt/__init__.py
macos_virt/constants.py
macos_virt/controller.py
macos_virt/main.py
macos_virt.egg-info/PKG-INFO
macos_virt.egg-info/SOURCES.txt
macos_virt.egg-info/dependency_links.txt
macos_virt.egg-info/entry_points.txt
macos_virt.egg-info/requires.txt
macos_virt.egg-info/top_level.txt
macos_virt/macos_virt_runner/macos_virt_runner
macos_virt/macos_virt_runner/macos_virt_runner.entitlements
macos_virt/profiles/__init__.py
macos_virt/profiles/downloader.py
macos_virt/profiles/registry.py
macos_virt/profiles/ubuntu-cloudinit.yaml
macos_virt/profiles/ubuntu.py
macos_virt/service/__init__.py
macos_virt/service/docker-service-override.conf
macos_virt/service/install_boot.sh
macos_virt/service/macos-virt-service.service
macos_virt/service/service.py