Metadata-Version: 2.1
Name: macos-virt
Version: 0.2.0
Summary: MacOS utility to run Linux using Virtualization.Framework
Home-page: https://github.com/dmarkey/macos-virt
Author: David Markey
Author-email: david@dmarkey.com
License: UNKNOWN
Platform: UNKNOWN
Classifier: Development Status :: 3 - Alpha
Classifier: License :: OSI Approved :: MIT License
License-File: LICENSE
